{
    "instance_file": "E1597202461634.txt",
    "total_cost": 784337.0,
    "total_routes": 3,
    "duration_seconds": 289.7314672470093,
    "routes": [
        {
            "route_id": 1,
            "vehicle_type": "CT03",
            "sequence_node_ids": [
                0,
                1,
                2,
                4,
                6,
                10,
                0
            ],
            "load_rate_volume": 0.7746627684374447,
            "distance": 466859.0,
            "items_count": 83,
            "has_bonded_node": false,
            "bonded_constraint_check": "N/A",
            "packed_items": [
                {
                    "item_id": "94264940102Q958",
                    "x": 0,
                    "y": 0,
                    "z": 0,
                    "lx": 1380,
                    "ly": 380,
                    "lz": 1550
                },
                {
                    "item_id": "94264940102Q957",
                    "x": 0,
                    "y": 380,
                    "z": 0,
                    "lx": 1380,
                    "ly": 380,
                    "lz": 1550
                },
                {
                    "item_id": "94264940102Q956",
                    "x": 0,
                    "y": 760,
                    "z": 0,
                    "lx": 1380,
                    "ly": 380,
                    "lz": 1550
                },
                {
                    "item_id": "94264940102Q955",
                    "x": 0,
                    "y": 1140,
                    "z": 0,
                    "lx": 1380,
                    "ly": 380,
                    "lz": 1550
                },
                {
                    "item_id": "94264940102Q954",
                    "x": 0,
                    "y": 1520,
                    "z": 0,
                    "lx": 1380,
                    "ly": 380,
                    "lz": 1550
                },
                {
                    "item_id": "94264940102Q953",
                    "x": 0,
                    "y": 1900,
                    "z": 0,
                    "lx": 1380,
                    "ly": 380,
                    "lz": 1550
                },
                {
                    "item_id": "94264940102Q952",
                    "x": 0,
                    "y": 0,
                    "z": 1550,
                    "lx": 1380,
                    "ly": 1550,
                    "lz": 380
                },
                {
                    "item_id": "94264940102Q951",
                    "x": 0,
                    "y": 0,
                    "z": 1930,
                    "lx": 1380,
                    "ly": 1550,
                    "lz": 380
                },
                {
                    "item_id": "94264940102Q950",
                    "x": 1380,
                    "y": 0,
                    "z": 0,
                    "lx": 1380,
                    "ly": 380,
                    "lz": 1550
                },
                {
                    "item_id": "94264940102Q949",
                    "x": 1380,
                    "y": 380,
                    "z": 0,
                    "lx": 1380,
                    "ly": 380,
                    "lz": 1550
                },
                {
                    "item_id": "94264940102Q948",
                    "x": 1380,
                    "y": 760,
                    "z": 0,
                    "lx": 1380,
                    "ly": 380,
                    "lz": 1550
                },
                {
                    "item_id": "94264940102Q947",
                    "x": 1380,
                    "y": 1140,
                    "z": 0,
                    "lx": 1380,
                    "ly": 380,
                    "lz": 1550
                },
                {
                    "item_id": "94264940102Q946",
                    "x": 1380,
                    "y": 1520,
                    "z": 0,
                    "lx": 1380,
                    "ly": 380,
                    "lz": 1550
                },
                {
                    "item_id": "94264940102Q945",
                    "x": 1380,
                    "y": 1900,
                    "z": 0,
                    "lx": 1380,
                    "ly": 380,
                    "lz": 1550
                },
                {
                    "item_id": "94264940102Q944",
                    "x": 1380,
                    "y": 0,
                    "z": 1550,
                    "lx": 1380,
                    "ly": 1550,
                    "lz": 380
                },
                {
                    "item_id": "94264940102Q943",
                    "x": 1380,
                    "y": 0,
                    "z": 1930,
                    "lx": 1380,
                    "ly": 1550,
                    "lz": 380
                },
                {
                    "item_id": "94264940102Q942",
                    "x": 2760,
                    "y": 0,
                    "z": 0,
                    "lx": 1380,
                    "ly": 380,
                    "lz": 1550
                },
                {
                    "item_id": "94264940102Q941",
                    "x": 2760,
                    "y": 380,
                    "z": 0,
                    "lx": 1380,
                    "ly": 380,
                    "lz": 1550
                },
                {
                    "item_id": "94264940102Q940",
                    "x": 2760,
                    "y": 760,
                    "z": 0,
                    "lx": 1380,
                    "ly": 380,
                    "lz": 1550
                },
                {
                    "item_id": "94264940102Q939",
                    "x": 2760,
                    "y": 1140,
                    "z": 0,
                    "lx": 1380,
                    "ly": 380,
                    "lz": 1550
                },
                {
                    "item_id": "94264940102Q938",
                    "x": 2760,
                    "y": 1520,
                    "z": 0,
                    "lx": 1380,
                    "ly": 380,
                    "lz": 1550
                },
                {
                    "item_id": "94264940102Q937",
                    "x": 2760,
                    "y": 1900,
                    "z": 0,
                    "lx": 1380,
                    "ly": 380,
                    "lz": 1550
                },
                {
                    "item_id": "94264940102Q936",
                    "x": 2760,
                    "y": 0,
                    "z": 1550,
                    "lx": 1380,
                    "ly": 1550,
                    "lz": 380
                },
                {
                    "item_id": "94264940102Q935",
                    "x": 2760,
                    "y": 0,
                    "z": 1930,
                    "lx": 1380,
                    "ly": 1550,
                    "lz": 380
                },
                {
                    "item_id": "94264940102Q934",
                    "x": 4140,
                    "y": 0,
                    "z": 0,
                    "lx": 1380,
                    "ly": 380,
                    "lz": 1550
                },
                {
                    "item_id": "94264940102Q933",
                    "x": 4140,
                    "y": 380,
                    "z": 0,
                    "lx": 1380,
                    "ly": 380,
                    "lz": 1550
                },
                {
                    "item_id": "94264940102Q932",
                    "x": 4140,
                    "y": 760,
                    "z": 0,
                    "lx": 1380,
                    "ly": 380,
                    "lz": 1550
                },
                {
                    "item_id": "94264940102Q931",
                    "x": 4140,
                    "y": 1140,
                    "z": 0,
                    "lx": 1380,
                    "ly": 380,
                    "lz": 1550
                },
                {
                    "item_id": "94264940102Q930",
                    "x": 4140,
                    "y": 1520,
                    "z": 0,
                    "lx": 1380,
                    "ly": 380,
                    "lz": 1550
                },
                {
                    "item_id": "94264940102Q929",
                    "x": 4140,
                    "y": 1900,
                    "z": 0,
                    "lx": 1380,
                    "ly": 380,
                    "lz": 1550
                },
                {
                    "item_id": "94264940102Q928",
                    "x": 4140,
                    "y": 0,
                    "z": 1550,
                    "lx": 1380,
                    "ly": 1550,
                    "lz": 380
                },
                {
                    "item_id": "94264940102Q965",
                    "x": 0,
                    "y": 1550,
                    "z": 1550,
                    "lx": 340,
                    "ly": 330,
                    "lz": 600
                },
                {
                    "item_id": "94264940102Q964",
                    "x": 0,
                    "y": 1880,
                    "z": 1550,
                    "lx": 340,
                    "ly": 330,
                    "lz": 600
                },
                {
                    "item_id": "94264940102Q963",
                    "x": 0,
                    "y": 1550,
                    "z": 2150,
                    "lx": 330,
                    "ly": 600,
                    "lz": 340
                },
                {
                    "item_id": "94264940102Q962",
                    "x": 340,
                    "y": 1550,
                    "z": 1550,
                    "lx": 340,
                    "ly": 330,
                    "lz": 600
                },
                {
                    "item_id": "94264940102Q961",
                    "x": 340,
                    "y": 1880,
                    "z": 1550,
                    "lx": 340,
                    "ly": 330,
                    "lz": 600
                },
                {
                    "item_id": "94264940102Q960",
                    "x": 330,
                    "y": 1550,
                    "z": 2150,
                    "lx": 330,
                    "ly": 600,
                    "lz": 340
                },
                {
                    "item_id": "94264940102Q959",
                    "x": 680,
                    "y": 1550,
                    "z": 1550,
                    "lx": 340,
                    "ly": 330,
                    "lz": 600
                },
                {
                    "item_id": "94264940102N928",
                    "x": 5520,
                    "y": 0,
                    "z": 0,
                    "lx": 2982,
                    "ly": 1140,
                    "lz": 1242
                },
                {
                    "item_id": "94264940102N929",
                    "x": 5520,
                    "y": 1140,
                    "z": 0,
                    "lx": 2982,
                    "ly": 1139,
                    "lz": 422
                },
                {
                    "item_id": "94264940102N930",
                    "x": 0,
                    "y": 0,
                    "z": 2310,
                    "lx": 2960,
                    "ly": 547,
                    "lz": 275
                },
                {
                    "item_id": "94264940102Q784",
                    "x": 5520,
                    "y": 1140,
                    "z": 422,
                    "lx": 1200,
                    "ly": 1000,
                    "lz": 1080
                },
                {
                    "item_id": "94264940102Q783",
                    "x": 5520,
                    "y": 0,
                    "z": 1242,
                    "lx": 1200,
                    "ly": 1000,
                    "lz": 1080
                },
                {
                    "item_id": "94264940102Q782",
                    "x": 5520,
                    "y": 1140,
                    "z": 1502,
                    "lx": 1200,
                    "ly": 1000,
                    "lz": 1080
                },
                {
                    "item_id": "94264940102Q781",
                    "x": 6720,
                    "y": 1140,
                    "z": 422,
                    "lx": 1200,
                    "ly": 1000,
                    "lz": 1080
                },
                {
                    "item_id": "94264940102Q780",
                    "x": 6720,
                    "y": 0,
                    "z": 1242,
                    "lx": 1200,
                    "ly": 1000,
                    "lz": 1080
                },
                {
                    "item_id": "94264940102Q779",
                    "x": 6720,
                    "y": 1140,
                    "z": 1502,
                    "lx": 1200,
                    "ly": 1000,
                    "lz": 1080
                },
                {
                    "item_id": "94264940102Q778",
                    "x": 8502,
                    "y": 0,
                    "z": 0,
                    "lx": 1075,
                    "ly": 1000,
                    "lz": 1200
                },
                {
                    "item_id": "94264940102Q333",
                    "x": 680,
                    "y": 1880,
                    "z": 1550,
                    "lx": 370,
                    "ly": 340,
                    "lz": 490
                },
                {
                    "item_id": "94264940102Q349",
                    "x": 8502,
                    "y": 1000,
                    "z": 0,
                    "lx": 800,
                    "ly": 1207,
                    "lz": 1200
                },
                {
                    "item_id": "94264940102Q336",
                    "x": 8502,
                    "y": 0,
                    "z": 1200,
                    "lx": 1200,
                    "ly": 800,
                    "lz": 845
                },
                {
                    "item_id": "94264940102Q335",
                    "x": 8502,
                    "y": 800,
                    "z": 1200,
                    "lx": 845,
                    "ly": 1200,
                    "lz": 800
                },
                {
                    "item_id": "94264940102N952",
                    "x": 1380,
                    "y": 1550,
                    "z": 1550,
                    "lx": 1200,
                    "ly": 645,
                    "lz": 800
                },
                {
                    "item_id": "94264940102Q927",
                    "x": 2580,
                    "y": 1550,
                    "z": 1550,
                    "lx": 1200,
                    "ly": 645,
                    "lz": 800
                },
                {
                    "item_id": "94264940102Q926",
                    "x": 3780,
                    "y": 1550,
                    "z": 1550,
                    "lx": 1200,
                    "ly": 645,
                    "lz": 800
                },
                {
                    "item_id": "94264940102Q925",
                    "x": 4140,
                    "y": 0,
                    "z": 1930,
                    "lx": 1200,
                    "ly": 800,
                    "lz": 645
                },
                {
                    "item_id": "94264940102Q924",
                    "x": 9302,
                    "y": 1000,
                    "z": 0,
                    "lx": 645,
                    "ly": 1200,
                    "lz": 800
                },
                {
                    "item_id": "94264940102Q178",
                    "x": 8502,
                    "y": 800,
                    "z": 2000,
                    "lx": 800,
                    "ly": 1186,
                    "lz": 600
                },
                {
                    "item_id": "94264940102Q219",
                    "x": 7920,
                    "y": 1140,
                    "z": 422,
                    "lx": 573,
                    "ly": 800,
                    "lz": 1200
                },
                {
                    "item_id": "94264940102Q436",
                    "x": 9577,
                    "y": 0,
                    "z": 0,
                    "lx": 600,
                    "ly": 835,
                    "lz": 800
                },
                {
                    "item_id": "94264940102Q971",
                    "x": 4140,
                    "y": 800,
                    "z": 1930,
                    "lx": 782,
                    "ly": 402,
                    "lz": 550
                },
                {
                    "item_id": "94264940102Q972",
                    "x": 4980,
                    "y": 1550,
                    "z": 1550,
                    "lx": 402,
                    "ly": 550,
                    "lz": 782
                },
                {
                    "item_id": "94264940102Q977",
                    "x": 7920,
                    "y": 0,
                    "z": 1242,
                    "lx": 550,
                    "ly": 782,
                    "lz": 402
                },
                {
                    "item_id": "94264940102Q974",
                    "x": 7920,
                    "y": 1140,
                    "z": 1622,
                    "lx": 550,
                    "ly": 782,
                    "lz": 402
                },
                {
                    "item_id": "94264940102Q970",
                    "x": 7920,
                    "y": 0,
                    "z": 1644,
                    "lx": 550,
                    "ly": 782,
                    "lz": 402
                },
                {
                    "item_id": "94264940102Q973",
                    "x": 7920,
                    "y": 1140,
                    "z": 2024,
                    "lx": 550,
                    "ly": 782,
                    "lz": 402
                },
                {
                    "item_id": "94264940102Q401",
                    "x": 7920,
                    "y": 0,
                    "z": 2046,
                    "lx": 550,
                    "ly": 782,
                    "lz": 402
                },
                {
                    "item_id": "94264940102N951",
                    "x": 4922,
                    "y": 800,
                    "z": 1930,
                    "lx": 570,
                    "ly": 625,
                    "lz": 370
                },
                {
                    "item_id": "94264940102Q572",
                    "x": 8502,
                    "y": 0,
                    "z": 2045,
                    "lx": 385,
                    "ly": 785,
                    "lz": 405
                },
                {
                    "item_id": "94264940102Q217",
                    "x": 680,
                    "y": 1880,
                    "z": 2040,
                    "lx": 380,
                    "ly": 355,
                    "lz": 530
                },
                {
                    "item_id": "94264940102N774",
                    "x": 0,
                    "y": 547,
                    "z": 2310,
                    "lx": 234,
                    "ly": 439,
                    "lz": 202
                },
                {
                    "item_id": "94264940102Q177",
                    "x": 0,
                    "y": 986,
                    "z": 2310,
                    "lx": 385,
                    "ly": 355,
                    "lz": 100
                },
                {
                    "item_id": "94264940102Q170",
                    "x": 0,
                    "y": 2210,
                    "z": 1550,
                    "lx": 225,
                    "ly": 95,
                    "lz": 375
                },
                {
                    "item_id": "94264940102Q434",
                    "x": 0,
                    "y": 2210,
                    "z": 1925,
                    "lx": 225,
                    "ly": 95,
                    "lz": 375
                },
                {
                    "item_id": "94264940102Q291",
                    "x": 0,
                    "y": 1341,
                    "z": 2310,
                    "lx": 375,
                    "ly": 95,
                    "lz": 225
                },
                {
                    "item_id": "94264940102Q210",
                    "x": 0,
                    "y": 1436,
                    "z": 2310,
                    "lx": 375,
                    "ly": 95,
                    "lz": 225
                },
                {
                    "item_id": "94264940102Q257",
                    "x": 0,
                    "y": 986,
                    "z": 2410,
                    "lx": 375,
                    "ly": 225,
                    "lz": 95
                },
                {
                    "item_id": "94264940102Q570",
                    "x": 0,
                    "y": 1550,
                    "z": 2490,
                    "lx": 225,
                    "ly": 375,
                    "lz": 95
                },
                {
                    "item_id": "94264940102Q472",
                    "x": 0,
                    "y": 1925,
                    "z": 2490,
                    "lx": 375,
                    "ly": 225,
                    "lz": 95
                },
                {
                    "item_id": "94264940102Q526",
                    "x": 9947,
                    "y": 1000,
                    "z": 0,
                    "lx": 1360,
                    "ly": 1145,
                    "lz": 920
                },
                {
                    "item_id": "94264940102Q523",
                    "x": 9947,
                    "y": 1000,
                    "z": 920,
                    "lx": 1360,
                    "ly": 1145,
                    "lz": 920
                },
                {
                    "item_id": "94264940102Q522",
                    "x": 10177,
                    "y": 0,
                    "z": 0,
                    "lx": 1360,
                    "ly": 920,
                    "lz": 1145
                },
                {
                    "item_id": "94264940102Q432",
                    "x": 10177,
                    "y": 0,
                    "z": 1145,
                    "lx": 1360,
                    "ly": 920,
                    "lz": 1145
                }
            ]
        },
        {
            "route_id": 2,
            "vehicle_type": "CT03",
            "sequence_node_ids": [
                0,
                3,
                9,
                8,
                5,
                0
            ],
            "load_rate_volume": 0.6484141222478077,
            "distance": 190795.0,
            "items_count": 72,
            "has_bonded_node": false,
            "bonded_constraint_check": "N/A",
            "packed_items": [
                {
                    "item_id": "94264940102Q428",
                    "x": 0,
                    "y": 0,
                    "z": 0,
                    "lx": 1100,
                    "ly": 1100,
                    "lz": 1100
                },
                {
                    "item_id": "94264940102Q427",
                    "x": 0,
                    "y": 1100,
                    "z": 0,
                    "lx": 1100,
                    "ly": 1100,
                    "lz": 1100
                },
                {
                    "item_id": "94264940102Q426",
                    "x": 0,
                    "y": 0,
                    "z": 1100,
                    "lx": 1100,
                    "ly": 1100,
                    "lz": 1100
                },
                {
                    "item_id": "94264940102Q425",
                    "x": 0,
                    "y": 1100,
                    "z": 1100,
                    "lx": 1100,
                    "ly": 1100,
                    "lz": 1100
                },
                {
                    "item_id": "94264940102Q424",
                    "x": 1100,
                    "y": 0,
                    "z": 0,
                    "lx": 1100,
                    "ly": 1100,
                    "lz": 1100
                },
                {
                    "item_id": "94264940102Q423",
                    "x": 1100,
                    "y": 1100,
                    "z": 0,
                    "lx": 1100,
                    "ly": 1100,
                    "lz": 1100
                },
                {
                    "item_id": "94264940102R059",
                    "x": 1100,
                    "y": 0,
                    "z": 1100,
                    "lx": 1125,
                    "ly": 800,
                    "lz": 1200
                },
                {
                    "item_id": "94264940102R058",
                    "x": 1100,
                    "y": 800,
                    "z": 1100,
                    "lx": 1125,
                    "ly": 800,
                    "lz": 1200
                },
                {
                    "item_id": "94264940102R057",
                    "x": 2200,
                    "y": 0,
                    "z": 0,
                    "lx": 1200,
                    "ly": 1125,
                    "lz": 800
                },
                {
                    "item_id": "94264940102R056",
                    "x": 2200,
                    "y": 1125,
                    "z": 0,
                    "lx": 1200,
                    "ly": 1125,
                    "lz": 800
                },
                {
                    "item_id": "94264940102R055",
                    "x": 3400,
                    "y": 0,
                    "z": 0,
                    "lx": 1125,
                    "ly": 800,
                    "lz": 1200
                },
                {
                    "item_id": "94264940102R054",
                    "x": 3400,
                    "y": 800,
                    "z": 0,
                    "lx": 1125,
                    "ly": 800,
                    "lz": 1200
                },
                {
                    "item_id": "94264940102R053",
                    "x": 3400,
                    "y": 0,
                    "z": 1200,
                    "lx": 1125,
                    "ly": 800,
                    "lz": 1200
                },
                {
                    "item_id": "94264940102R052",
                    "x": 3400,
                    "y": 800,
                    "z": 1200,
                    "lx": 1125,
                    "ly": 800,
                    "lz": 1200
                },
                {
                    "item_id": "94264940102R051",
                    "x": 4525,
                    "y": 0,
                    "z": 0,
                    "lx": 1125,
                    "ly": 800,
                    "lz": 1200
                },
                {
                    "item_id": "94264940102R050",
                    "x": 4525,
                    "y": 800,
                    "z": 0,
                    "lx": 1125,
                    "ly": 800,
                    "lz": 1200
                },
                {
                    "item_id": "94264940102R049",
                    "x": 4525,
                    "y": 0,
                    "z": 1200,
                    "lx": 1125,
                    "ly": 800,
                    "lz": 1200
                },
                {
                    "item_id": "94264940102R048",
                    "x": 4525,
                    "y": 800,
                    "z": 1200,
                    "lx": 1125,
                    "ly": 800,
                    "lz": 1200
                },
                {
                    "item_id": "94264940102R047",
                    "x": 5650,
                    "y": 0,
                    "z": 0,
                    "lx": 1125,
                    "ly": 800,
                    "lz": 1200
                },
                {
                    "item_id": "94264940102R046",
                    "x": 5650,
                    "y": 800,
                    "z": 0,
                    "lx": 1125,
                    "ly": 800,
                    "lz": 1200
                },
                {
                    "item_id": "94264940102Q429",
                    "x": 0,
                    "y": 0,
                    "z": 2200,
                    "lx": 1100,
                    "ly": 1100,
                    "lz": 375
                },
                {
                    "item_id": "94264940102R060",
                    "x": 0,
                    "y": 1100,
                    "z": 2200,
                    "lx": 800,
                    "ly": 1200,
                    "lz": 180
                },
                {
                    "item_id": "94264940102R061",
                    "x": 0,
                    "y": 2200,
                    "z": 0,
                    "lx": 387,
                    "ly": 45,
                    "lz": 387
                },
                {
                    "item_id": "94264940102Q169",
                    "x": 1100,
                    "y": 1600,
                    "z": 1100,
                    "lx": 1200,
                    "ly": 645,
                    "lz": 800
                },
                {
                    "item_id": "94264940102M891",
                    "x": 3400,
                    "y": 1600,
                    "z": 0,
                    "lx": 1200,
                    "ly": 645,
                    "lz": 800
                },
                {
                    "item_id": "94264940102Q168",
                    "x": 3400,
                    "y": 1600,
                    "z": 800,
                    "lx": 1200,
                    "ly": 645,
                    "lz": 800
                },
                {
                    "item_id": "94264940102N427",
                    "x": 3400,
                    "y": 1600,
                    "z": 1600,
                    "lx": 985,
                    "ly": 600,
                    "lz": 800
                },
                {
                    "item_id": "94264940102N426",
                    "x": 4600,
                    "y": 1600,
                    "z": 0,
                    "lx": 985,
                    "ly": 600,
                    "lz": 800
                },
                {
                    "item_id": "94264940102N425",
                    "x": 4600,
                    "y": 1600,
                    "z": 800,
                    "lx": 985,
                    "ly": 600,
                    "lz": 800
                },
                {
                    "item_id": "94264940102N424",
                    "x": 4385,
                    "y": 1600,
                    "z": 1600,
                    "lx": 985,
                    "ly": 600,
                    "lz": 800
                },
                {
                    "item_id": "94264940102N423",
                    "x": 5585,
                    "y": 1600,
                    "z": 0,
                    "lx": 985,
                    "ly": 600,
                    "lz": 800
                },
                {
                    "item_id": "94264940102N422",
                    "x": 5585,
                    "y": 1600,
                    "z": 800,
                    "lx": 985,
                    "ly": 600,
                    "lz": 800
                },
                {
                    "item_id": "94264940102N282",
                    "x": 5370,
                    "y": 1600,
                    "z": 1600,
                    "lx": 985,
                    "ly": 600,
                    "lz": 800
                },
                {
                    "item_id": "94264940102N281",
                    "x": 5650,
                    "y": 0,
                    "z": 1200,
                    "lx": 600,
                    "ly": 985,
                    "lz": 800
                },
                {
                    "item_id": "94264940102N280",
                    "x": 5650,
                    "y": 985,
                    "z": 1200,
                    "lx": 985,
                    "ly": 600,
                    "lz": 800
                },
                {
                    "item_id": "94264940102N279",
                    "x": 6250,
                    "y": 0,
                    "z": 1200,
                    "lx": 600,
                    "ly": 985,
                    "lz": 800
                },
                {
                    "item_id": "94264940102N278",
                    "x": 5650,
                    "y": 0,
                    "z": 2000,
                    "lx": 800,
                    "ly": 985,
                    "lz": 600
                },
                {
                    "item_id": "94264940102N277",
                    "x": 6570,
                    "y": 1600,
                    "z": 0,
                    "lx": 985,
                    "ly": 600,
                    "lz": 800
                },
                {
                    "item_id": "94264940102N276",
                    "x": 6570,
                    "y": 1600,
                    "z": 800,
                    "lx": 985,
                    "ly": 600,
                    "lz": 800
                },
                {
                    "item_id": "94264940102N275",
                    "x": 6355,
                    "y": 1600,
                    "z": 1600,
                    "lx": 985,
                    "ly": 600,
                    "lz": 800
                },
                {
                    "item_id": "94264940102N274",
                    "x": 6775,
                    "y": 0,
                    "z": 0,
                    "lx": 600,
                    "ly": 985,
                    "lz": 800
                },
                {
                    "item_id": "94264940102N273",
                    "x": 6775,
                    "y": 985,
                    "z": 0,
                    "lx": 985,
                    "ly": 600,
                    "lz": 800
                },
                {
                    "item_id": "94264940102N942",
                    "x": 6775,
                    "y": 985,
                    "z": 800,
                    "lx": 985,
                    "ly": 600,
                    "lz": 800
                },
                {
                    "item_id": "94264940102N941",
                    "x": 6775,
                    "y": 985,
                    "z": 1600,
                    "lx": 985,
                    "ly": 600,
                    "lz": 800
                },
                {
                    "item_id": "94264940102N940",
                    "x": 7375,
                    "y": 0,
                    "z": 0,
                    "lx": 600,
                    "ly": 985,
                    "lz": 800
                },
                {
                    "item_id": "94264940102N939",
                    "x": 7375,
                    "y": 0,
                    "z": 800,
                    "lx": 600,
                    "ly": 985,
                    "lz": 800
                },
                {
                    "item_id": "94264940102N938",
                    "x": 7375,
                    "y": 0,
                    "z": 1600,
                    "lx": 600,
                    "ly": 985,
                    "lz": 800
                },
                {
                    "item_id": "94264940102N937",
                    "x": 7555,
                    "y": 1600,
                    "z": 0,
                    "lx": 985,
                    "ly": 600,
                    "lz": 800
                },
                {
                    "item_id": "94264940102N936",
                    "x": 7555,
                    "y": 1600,
                    "z": 800,
                    "lx": 985,
                    "ly": 600,
                    "lz": 800
                },
                {
                    "item_id": "94264940102N935",
                    "x": 7340,
                    "y": 1600,
                    "z": 1600,
                    "lx": 985,
                    "ly": 600,
                    "lz": 800
                },
                {
                    "item_id": "94264940102N429",
                    "x": 1100,
                    "y": 1600,
                    "z": 1900,
                    "lx": 800,
                    "ly": 600,
                    "lz": 700
                },
                {
                    "item_id": "94264940102N428",
                    "x": 7760,
                    "y": 985,
                    "z": 0,
                    "lx": 800,
                    "ly": 600,
                    "lz": 700
                },
                {
                    "item_id": "94264940102N944",
                    "x": 7760,
                    "y": 985,
                    "z": 700,
                    "lx": 800,
                    "ly": 600,
                    "lz": 700
                },
                {
                    "item_id": "94264940102N943",
                    "x": 7760,
                    "y": 985,
                    "z": 1400,
                    "lx": 800,
                    "ly": 600,
                    "lz": 700
                },
                {
                    "item_id": "94264940102N945",
                    "x": 7975,
                    "y": 0,
                    "z": 0,
                    "lx": 600,
                    "ly": 700,
                    "lz": 800
                },
                {
                    "item_id": "94264940102Q921",
                    "x": 5650,
                    "y": 985,
                    "z": 2000,
                    "lx": 782,
                    "ly": 402,
                    "lz": 550
                },
                {
                    "item_id": "94264940102Q473",
                    "x": 1900,
                    "y": 1600,
                    "z": 1900,
                    "lx": 400,
                    "ly": 355,
                    "lz": 600
                },
                {
                    "item_id": "94264940102Q474",
                    "x": 6450,
                    "y": 0,
                    "z": 2000,
                    "lx": 380,
                    "ly": 355,
                    "lz": 530
                },
                {
                    "item_id": "94264940102Q293",
                    "x": 0,
                    "y": 1100,
                    "z": 2380,
                    "lx": 410,
                    "ly": 410,
                    "lz": 160
                },
                {
                    "item_id": "94264940102N824",
                    "x": 8560,
                    "y": 985,
                    "z": 0,
                    "lx": 1200,
                    "ly": 1215,
                    "lz": 800
                },
                {
                    "item_id": "94264940102P012",
                    "x": 8575,
                    "y": 0,
                    "z": 0,
                    "lx": 1020,
                    "ly": 800,
                    "lz": 1200
                },
                {
                    "item_id": "94264940102Q433",
                    "x": 8560,
                    "y": 985,
                    "z": 800,
                    "lx": 1200,
                    "ly": 800,
                    "lz": 845
                },
                {
                    "item_id": "94264940102Q525",
                    "x": 8575,
                    "y": 0,
                    "z": 1200,
                    "lx": 630,
                    "ly": 920,
                    "lz": 1360
                },
                {
                    "item_id": "94264940102Q524",
                    "x": 8560,
                    "y": 985,
                    "z": 1645,
                    "lx": 1200,
                    "ly": 800,
                    "lz": 645
                },
                {
                    "item_id": "94264940102Q749",
                    "x": 9595,
                    "y": 0,
                    "z": 0,
                    "lx": 1200,
                    "ly": 800,
                    "lz": 645
                },
                {
                    "item_id": "94264940102N807",
                    "x": 7975,
                    "y": 0,
                    "z": 800,
                    "lx": 600,
                    "ly": 800,
                    "lz": 1190
                },
                {
                    "item_id": "94264940102Q521",
                    "x": 8560,
                    "y": 1785,
                    "z": 800,
                    "lx": 1360,
                    "ly": 390,
                    "lz": 920
                },
                {
                    "item_id": "94264940102N806",
                    "x": 9595,
                    "y": 0,
                    "z": 645,
                    "lx": 800,
                    "ly": 600,
                    "lz": 1000
                },
                {
                    "item_id": "94264940102Q812",
                    "x": 9595,
                    "y": 0,
                    "z": 1645,
                    "lx": 835,
                    "ly": 600,
                    "lz": 800
                },
                {
                    "item_id": "94264940102Q882",
                    "x": 9760,
                    "y": 985,
                    "z": 0,
                    "lx": 600,
                    "ly": 835,
                    "lz": 800
                },
                {
                    "item_id": "94264940102Q286",
                    "x": 9760,
                    "y": 985,
                    "z": 800,
                    "lx": 540,
                    "ly": 670,
                    "lz": 630
                },
                {
                    "item_id": "94264940102Q483",
                    "x": 0,
                    "y": 1510,
                    "z": 2380,
                    "lx": 430,
                    "ly": 670,
                    "lz": 170
                }
            ]
        },
        {
            "route_id": 3,
            "vehicle_type": "R110",
            "sequence_node_ids": [
                0,
                7,
                0
            ],
            "load_rate_volume": 0.40220504879729146,
            "distance": 126683.0,
            "items_count": 19,
            "has_bonded_node": false,
            "bonded_constraint_check": "N/A",
            "packed_items": [
                {
                    "item_id": "94264940102Q545",
                    "x": 0,
                    "y": 0,
                    "z": 0,
                    "lx": 1154,
                    "ly": 754,
                    "lz": 754
                },
                {
                    "item_id": "94264940102Q544",
                    "x": 0,
                    "y": 754,
                    "z": 0,
                    "lx": 1154,
                    "ly": 754,
                    "lz": 754
                },
                {
                    "item_id": "94264940102Q543",
                    "x": 0,
                    "y": 1508,
                    "z": 0,
                    "lx": 1154,
                    "ly": 754,
                    "lz": 754
                },
                {
                    "item_id": "94264940102Q542",
                    "x": 0,
                    "y": 0,
                    "z": 754,
                    "lx": 1154,
                    "ly": 754,
                    "lz": 754
                },
                {
                    "item_id": "94264940102Q541",
                    "x": 0,
                    "y": 754,
                    "z": 754,
                    "lx": 1154,
                    "ly": 754,
                    "lz": 754
                },
                {
                    "item_id": "94264940102Q540",
                    "x": 0,
                    "y": 1508,
                    "z": 754,
                    "lx": 1154,
                    "ly": 754,
                    "lz": 754
                },
                {
                    "item_id": "94264940102Q539",
                    "x": 0,
                    "y": 0,
                    "z": 1508,
                    "lx": 1154,
                    "ly": 754,
                    "lz": 754
                },
                {
                    "item_id": "94264940102Q538",
                    "x": 0,
                    "y": 754,
                    "z": 1508,
                    "lx": 1154,
                    "ly": 754,
                    "lz": 754
                },
                {
                    "item_id": "94264940102Q537",
                    "x": 0,
                    "y": 1508,
                    "z": 1508,
                    "lx": 1154,
                    "ly": 754,
                    "lz": 754
                },
                {
                    "item_id": "94264940102Q536",
                    "x": 1154,
                    "y": 0,
                    "z": 0,
                    "lx": 1154,
                    "ly": 754,
                    "lz": 754
                },
                {
                    "item_id": "94264940102Q535",
                    "x": 1154,
                    "y": 754,
                    "z": 0,
                    "lx": 1154,
                    "ly": 754,
                    "lz": 754
                },
                {
                    "item_id": "94264940102Q534",
                    "x": 1154,
                    "y": 1508,
                    "z": 0,
                    "lx": 1154,
                    "ly": 754,
                    "lz": 754
                },
                {
                    "item_id": "94264940102Q533",
                    "x": 1154,
                    "y": 0,
                    "z": 754,
                    "lx": 1154,
                    "ly": 754,
                    "lz": 754
                },
                {
                    "item_id": "94264940102Q532",
                    "x": 1154,
                    "y": 754,
                    "z": 754,
                    "lx": 1154,
                    "ly": 754,
                    "lz": 754
                },
                {
                    "item_id": "94264940102Q531",
                    "x": 1154,
                    "y": 1508,
                    "z": 754,
                    "lx": 1154,
                    "ly": 754,
                    "lz": 754
                },
                {
                    "item_id": "94264940102Q530",
                    "x": 1154,
                    "y": 0,
                    "z": 1508,
                    "lx": 1154,
                    "ly": 754,
                    "lz": 754
                },
                {
                    "item_id": "94264940102Q529",
                    "x": 1154,
                    "y": 754,
                    "z": 1508,
                    "lx": 1154,
                    "ly": 754,
                    "lz": 754
                },
                {
                    "item_id": "94264940102Q528",
                    "x": 1154,
                    "y": 1508,
                    "z": 1508,
                    "lx": 1154,
                    "ly": 754,
                    "lz": 754
                },
                {
                    "item_id": "94264940102Q527",
                    "x": 2308,
                    "y": 0,
                    "z": 0,
                    "lx": 1154,
                    "ly": 754,
                    "lz": 754
                }
            ]
        }
    ]
}