{
    "instance_file": "EF1595381687057.txt",
    "total_cost": 218777.0,
    "total_routes": 1,
    "duration_seconds": 6.304636001586914,
    "routes": [
        {
            "route_id": 1,
            "vehicle_type": "CT10",
            "sequence_node_ids": [
                0,
                3,
                5,
                7,
                0
            ],
            "load_rate_volume": 0.3885570802061802,
            "distance": 218777.0,
            "items_count": 53,
            "has_bonded_node": false,
            "bonded_constraint_check": "N/A",
            "packed_items": [
                {
                    "item_id": "942615201015845",
                    "x": 0,
                    "y": 0,
                    "z": 0,
                    "lx": 1040,
                    "ly": 460,
                    "lz": 1130
                },
                {
                    "item_id": "942615201015883",
                    "x": 0,
                    "y": 460,
                    "z": 0,
                    "lx": 730,
                    "ly": 730,
                    "lz": 560
                },
                {
                    "item_id": "942615201015844",
                    "x": 0,
                    "y": 1190,
                    "z": 0,
                    "lx": 1127,
                    "ly": 528,
                    "lz": 460
                },
                {
                    "item_id": "942615201015843",
                    "x": 0,
                    "y": 1718,
                    "z": 0,
                    "lx": 800,
                    "ly": 451,
                    "lz": 595
                },
                {
                    "item_id": "942615201015842",
                    "x": 0,
                    "y": 1190,
                    "z": 460,
                    "lx": 410,
                    "ly": 450,
                    "lz": 595
                },
                {
                    "item_id": "942615201015972",
                    "x": 0,
                    "y": 460,
                    "z": 560,
                    "lx": 420,
                    "ly": 420,
                    "lz": 210
                },
                {
                    "item_id": "942615201015975",
                    "x": 0,
                    "y": 880,
                    "z": 560,
                    "lx": 420,
                    "ly": 170,
                    "lz": 420
                },
                {
                    "item_id": "942615201015977",
                    "x": 0,
                    "y": 1718,
                    "z": 595,
                    "lx": 200,
                    "ly": 380,
                    "lz": 380
                },
                {
                    "item_id": "942615201015982",
                    "x": 0,
                    "y": 460,
                    "z": 770,
                    "lx": 200,
                    "ly": 380,
                    "lz": 380
                },
                {
                    "item_id": "942615201016081",
                    "x": 0,
                    "y": 880,
                    "z": 980,
                    "lx": 360,
                    "ly": 150,
                    "lz": 360
                },
                {
                    "item_id": "942615201016068",
                    "x": 0,
                    "y": 1718,
                    "z": 975,
                    "lx": 150,
                    "ly": 360,
                    "lz": 360
                },
                {
                    "item_id": "942615201016086",
                    "x": 0,
                    "y": 1190,
                    "z": 1055,
                    "lx": 360,
                    "ly": 360,
                    "lz": 150
                },
                {
                    "item_id": "942615201016090",
                    "x": 200,
                    "y": 1718,
                    "z": 595,
                    "lx": 560,
                    "ly": 585,
                    "lz": 880
                },
                {
                    "item_id": "942615201016089",
                    "x": 730,
                    "y": 460,
                    "z": 0,
                    "lx": 560,
                    "ly": 585,
                    "lz": 880
                },
                {
                    "item_id": "942615201016065",
                    "x": 800,
                    "y": 1718,
                    "z": 0,
                    "lx": 560,
                    "ly": 585,
                    "lz": 880
                },
                {
                    "item_id": "942615201016064",
                    "x": 730,
                    "y": 460,
                    "z": 880,
                    "lx": 560,
                    "ly": 585,
                    "lz": 880
                },
                {
                    "item_id": "942615201016088",
                    "x": 800,
                    "y": 1718,
                    "z": 880,
                    "lx": 560,
                    "ly": 585,
                    "lz": 880
                },
                {
                    "item_id": "942615201016087",
                    "x": 1290,
                    "y": 460,
                    "z": 0,
                    "lx": 585,
                    "ly": 880,
                    "lz": 560
                },
                {
                    "item_id": "942615201015987",
                    "x": 0,
                    "y": 0,
                    "z": 1130,
                    "lx": 735,
                    "ly": 405,
                    "lz": 785
                },
                {
                    "item_id": "942615201015846",
                    "x": 0,
                    "y": 1190,
                    "z": 1205,
                    "lx": 383,
                    "ly": 440,
                    "lz": 605
                },
                {
                    "item_id": "942615201016085",
                    "x": 0,
                    "y": 460,
                    "z": 1150,
                    "lx": 235,
                    "ly": 365,
                    "lz": 375
                },
                {
                    "item_id": "942615201016078",
                    "x": 0,
                    "y": 460,
                    "z": 1525,
                    "lx": 235,
                    "ly": 365,
                    "lz": 375
                },
                {
                    "item_id": "942615201016025",
                    "x": 0,
                    "y": 1190,
                    "z": 1810,
                    "lx": 375,
                    "ly": 365,
                    "lz": 235
                },
                {
                    "item_id": "942615201015884",
                    "x": 0,
                    "y": 880,
                    "z": 1340,
                    "lx": 365,
                    "ly": 175,
                    "lz": 375
                },
                {
                    "item_id": "942615201015890",
                    "x": 0,
                    "y": 1718,
                    "z": 1335,
                    "lx": 175,
                    "ly": 375,
                    "lz": 365
                },
                {
                    "item_id": "942615201015974",
                    "x": 0,
                    "y": 1718,
                    "z": 1700,
                    "lx": 175,
                    "ly": 375,
                    "lz": 365
                },
                {
                    "item_id": "942615201015880",
                    "x": 0,
                    "y": 880,
                    "z": 1715,
                    "lx": 340,
                    "ly": 170,
                    "lz": 340
                },
                {
                    "item_id": "942615201015976",
                    "x": 0,
                    "y": 460,
                    "z": 1900,
                    "lx": 170,
                    "ly": 340,
                    "lz": 340
                },
                {
                    "item_id": "942615201016082",
                    "x": 0,
                    "y": 2169,
                    "z": 0,
                    "lx": 385,
                    "ly": 100,
                    "lz": 355
                },
                {
                    "item_id": "942615201016084",
                    "x": 0,
                    "y": 1050,
                    "z": 560,
                    "lx": 385,
                    "ly": 100,
                    "lz": 355
                },
                {
                    "item_id": "942615201016067",
                    "x": 0,
                    "y": 1050,
                    "z": 915,
                    "lx": 385,
                    "ly": 100,
                    "lz": 355
                },
                {
                    "item_id": "942615201016069",
                    "x": 0,
                    "y": 0,
                    "z": 1915,
                    "lx": 385,
                    "ly": 100,
                    "lz": 355
                },
                {
                    "item_id": "942615201016077",
                    "x": 0,
                    "y": 100,
                    "z": 1915,
                    "lx": 385,
                    "ly": 100,
                    "lz": 355
                },
                {
                    "item_id": "942615201016079",
                    "x": 0,
                    "y": 200,
                    "z": 1915,
                    "lx": 385,
                    "ly": 100,
                    "lz": 355
                },
                {
                    "item_id": "942615201016080",
                    "x": 0,
                    "y": 2169,
                    "z": 355,
                    "lx": 375,
                    "ly": 95,
                    "lz": 225
                },
                {
                    "item_id": "942615201016083",
                    "x": 0,
                    "y": 300,
                    "z": 1915,
                    "lx": 375,
                    "ly": 95,
                    "lz": 225
                },
                {
                    "item_id": "942615201016076",
                    "x": 0,
                    "y": 1190,
                    "z": 2045,
                    "lx": 95,
                    "ly": 375,
                    "lz": 225
                },
                {
                    "item_id": "942615201016133",
                    "x": 1875,
                    "y": 460,
                    "z": 0,
                    "lx": 1060,
                    "ly": 1120,
                    "lz": 1120
                },
                {
                    "item_id": "942615201016132",
                    "x": 1875,
                    "y": 460,
                    "z": 1120,
                    "lx": 1060,
                    "ly": 1120,
                    "lz": 1120
                },
                {
                    "item_id": "942615201016131",
                    "x": 2935,
                    "y": 460,
                    "z": 0,
                    "lx": 1060,
                    "ly": 1120,
                    "lz": 1120
                },
                {
                    "item_id": "942615201016130",
                    "x": 2935,
                    "y": 460,
                    "z": 1120,
                    "lx": 1060,
                    "ly": 1120,
                    "lz": 1120
                },
                {
                    "item_id": "942615201016129",
                    "x": 3995,
                    "y": 460,
                    "z": 0,
                    "lx": 1060,
                    "ly": 1120,
                    "lz": 1120
                },
                {
                    "item_id": "942615201016128",
                    "x": 3995,
                    "y": 460,
                    "z": 1120,
                    "lx": 1060,
                    "ly": 1120,
                    "lz": 1120
                },
                {
                    "item_id": "942615201016127",
                    "x": 5055,
                    "y": 460,
                    "z": 0,
                    "lx": 1060,
                    "ly": 1120,
                    "lz": 1120
                },
                {
                    "item_id": "942615201016126",
                    "x": 5055,
                    "y": 460,
                    "z": 1120,
                    "lx": 1060,
                    "ly": 1120,
                    "lz": 1120
                },
                {
                    "item_id": "942615201016125",
                    "x": 6115,
                    "y": 460,
                    "z": 0,
                    "lx": 1060,
                    "ly": 1120,
                    "lz": 1120
                },
                {
                    "item_id": "942615201016124",
                    "x": 6115,
                    "y": 460,
                    "z": 1120,
                    "lx": 1060,
                    "ly": 1120,
                    "lz": 1120
                },
                {
                    "item_id": "942615201016123",
                    "x": 7175,
                    "y": 460,
                    "z": 0,
                    "lx": 1060,
                    "ly": 1120,
                    "lz": 1120
                },
                {
                    "item_id": "942615201016122",
                    "x": 7175,
                    "y": 460,
                    "z": 1120,
                    "lx": 1060,
                    "ly": 1120,
                    "lz": 1120
                },
                {
                    "item_id": "942615201016121",
                    "x": 8235,
                    "y": 460,
                    "z": 0,
                    "lx": 1060,
                    "ly": 1120,
                    "lz": 1120
                },
                {
                    "item_id": "942615201016120",
                    "x": 8235,
                    "y": 460,
                    "z": 1120,
                    "lx": 1060,
                    "ly": 1120,
                    "lz": 1120
                },
                {
                    "item_id": "942615201016119",
                    "x": 9295,
                    "y": 460,
                    "z": 0,
                    "lx": 1060,
                    "ly": 1120,
                    "lz": 1120
                },
                {
                    "item_id": "942615201016134",
                    "x": 1040,
                    "y": 0,
                    "z": 0,
                    "lx": 1120,
                    "ly": 340,
                    "lz": 1120
                }
            ]
        }
    ]
}